nrd/__init__.py
nrd/nrd.py
nrd/service_manager.py
nrd/sites.py
nrd-0.0.12.dist-info/licenses/LICENSE
nrd-0.0.12.dist-info/METADATA
nrd-0.0.12.dist-info/WHEEL
nrd-0.0.12.dist-info/entry_points.txt
nrd-0.0.12.dist-info/top_level.txt
nrd-0.0.12.dist-info/RECORD
