Metadata-Version: 2.4
Name: nrd
Version: 0.0.12
Summary: run vite dev server in background
Author-email: Problemli GmbH <info@problem.li>
Project-URL: Homepage, https://github.com/blemli/nrd2
Project-URL: Issues, https://github.com/blemli/nrd2
Classifier: Programming Language :: Python :: 3
Classifier: License :: OSI Approved :: MIT License
Classifier: Operating System :: OS Independent
Requires-Python: >=3.8
License-File: LICENSE
Requires-Dist: icecream>=2.1.0
Dynamic: license-file
